CHANGELOG.md
LICENSE
README.md
REFERENCE.md
docs/encoder.md
docs/motor.md
docs/servo.md
ioexpander/__init__.py
ioexpander/common.py
ioexpander/devices.py
ioexpander/encoder.py
ioexpander/ioe_regs.py
ioexpander/motor.py
ioexpander/servo.py
ioexpander/sioe_regs.py
pimoroni_ioexpander-1.0.1.dist-info/METADATA
pimoroni_ioexpander-1.0.1.dist-info/WHEEL
pimoroni_ioexpander-1.0.1.dist-info/licenses/LICENSE
pimoroni_ioexpander-1.0.1.dist-info/RECORD
